{
    "products": [
        {
            "id": "b6693472-9561-4e04-af44-0afee5411760",
            "name": "test",
            "type": "test",
            "price": "30",
            "manufacturer": "Coop",
            "quantityType": "Stk"
        },
        {
            "id": "b6693472-9561-4e04-af44-0afee5411760",
            "name": "test",
            "type": "test",
            "price": "1",
            "manufacturer": "Migros",
            "quantityType": "Kg"
        },
        {
            "id": "bd3ac241-0159-481c-9391-7e5366ada27f",
            "name": "sdf",
            "type": "sdf",
            "price": "15",
            "manufacturer": "Migros",
            "quantityType": "Lt"
        }
    ],
    "orders": [
        {
            "id": 1,
            "name": "Mike",
            "wohnhaus": "Wohnhaus 1",
            "datum": "heute",
            "products": [
                1
            ]
        },
        {
            "id": "d37d7d05-ef72-4a23-bdd0-425856464313",
            "name": "hallo",
            "wohnhaus": "lskdjflkj",
            "datum": "2002-11-06",
            "products": []
        },
        {
            "id": "f97f934d-77e6-4cdc-839d-785d0ff555ae",
            "name": "sldkfjl",
            "wohnhaus": "hsdf",
            "datum": "2023-06-30",
            "products": []
        },
        {
            "id": "3c3d571d-4529-413b-afba-6bcecdd42335",
            "name": "sdf",
            "wohnhaus": "sdf",
            "datum": "2002-11-06",
            "products": []
        }
    ]
}